[{"model": "orderitem.orderitem", "pk": 149, "fields": {"product": 1, "product_name": "Latte", "quantity": 1}}, {"model": "orderitem.orderitem", "pk": 150, "fields": {"product": 1, "product_name": "Latte", "quantity": 1}}, {"model": "orderitem.orderitem", "pk": 151, "fields": {"product": 2, "product_name": "Cappuccino", "quantity": 3}}, {"model": "orderitem.orderitem", "pk": 152, "fields": {"product": 15, "product_name": "Still Water 500ml", "quantity": 1}}, {"model": "orderitem.orderitem", "pk": 153, "fields": {"product": 1, "product_name": "Latte", "quantity": 1}}, {"model": "orderitem.orderitem", "pk": 154, "fields": {"product": 6, "product_name": "Double Espresso", "quantity": 1}}, {"model": "orderitem.orderitem", "pk": 155, "fields": {"product": 7, "product_name": "Black Americano", "quantity": 1}}, {"model": "orderitem.orderitem", "pk": 156, "fields": {"product": 1, "product_name": "Latte", "quantity": 11}}, {"model": "orderitem.orderitem", "pk": 157, "fields": {"product": 2, "product_name": "Cappuccino", "quantity": 8}}, {"model": "orderitem.orderitem", "pk": 158, "fields": {"product": 3, "product_name": "Espresso", "quantity": 4}}, {"model": "orderitem.orderitem", "pk": 159, "fields": {"product": 8, "product_name": "White Americano", "quantity": 3}}, {"model": "orderitem.orderitem", "pk": 160, "fields": {"product": 9, "product_name": "Hot Chocolate", "quantity": 1}}, {"model": "orderitem.orderitem", "pk": 161, "fields": {"product": 4, "product_name": "Machiato", "quantity": 7}}, {"model": "orderitem.orderitem", "pk": 162, "fields": {"product": 5, "product_name": "Flat White", "quantity": 1}}, {"model": "orderitem.orderitem", "pk": 163, "fields": {"product": 10, "product_name": "English Tea", "quantity": 7}}, {"model": "orderitem.orderitem", "pk": 164, "fields": {"product": 1, "product_name": "Latte", "quantity": 2}}, {"model": "orderitem.orderitem", "pk": 165, "fields": {"product": 1, "product_name": "Latte", "quantity": 1}}, {"model": "orderitem.orderitem", "pk": 166, "fields": {"product": 1, "product_name": "Latte", "quantity": 1}}, {"model": "orderitem.orderitem", "pk": 167, "fields": {"product": 1, "product_name": "Latte", "quantity": 1}}, {"model": "orderitem.orderitem", "pk": 168, "fields": {"product": 1, "product_name": "Latte", "quantity": 1}}, {"model": "orderitem.orderitem", "pk": 169, "fields": {"product": 1, "product_name": "Latte", "quantity": 1}}, {"model": "orderitem.orderitem", "pk": 170, "fields": {"product": 1, "product_name": "Latte", "quantity": 7}}, {"model": "orderitem.orderitem", "pk": 171, "fields": {"product": 3, "product_name": "Espresso", "quantity": 6}}]